odoo/addons/account_invoice_overdue_reminder/README.rst
odoo/addons/account_invoice_overdue_reminder/__init__.py
odoo/addons/account_invoice_overdue_reminder/__manifest__.py
odoo/addons/account_invoice_overdue_reminder/hooks.py
odoo/addons/account_invoice_overdue_reminder/data/mail_template.xml
odoo/addons/account_invoice_overdue_reminder/data/overdue_reminder_result.xml
odoo/addons/account_invoice_overdue_reminder/i18n/account_invoice_overdue_reminder.pot
odoo/addons/account_invoice_overdue_reminder/i18n/fr.po
odoo/addons/account_invoice_overdue_reminder/i18n/it.po
odoo/addons/account_invoice_overdue_reminder/i18n/nl.po
odoo/addons/account_invoice_overdue_reminder/migrations/13.0.1.0.0/post-migration.py
odoo/addons/account_invoice_overdue_reminder/migrations/13.0.1.0.0/pre-migration.py
odoo/addons/account_invoice_overdue_reminder/models/__init__.py
odoo/addons/account_invoice_overdue_reminder/models/account_invoice_overdue_reminder.py
odoo/addons/account_invoice_overdue_reminder/models/account_move.py
odoo/addons/account_invoice_overdue_reminder/models/overdue_reminder_action.py
odoo/addons/account_invoice_overdue_reminder/models/overdue_reminder_result.py
odoo/addons/account_invoice_overdue_reminder/models/res_company.py
odoo/addons/account_invoice_overdue_reminder/models/res_partner.py
odoo/addons/account_invoice_overdue_reminder/readme/CONFIGURATION.rst
odoo/addons/account_invoice_overdue_reminder/readme/CONTRIBUTORS.rst
odoo/addons/account_invoice_overdue_reminder/readme/DESCRIPTION.rst
odoo/addons/account_invoice_overdue_reminder/readme/HISTORY.rst
odoo/addons/account_invoice_overdue_reminder/readme/USAGE.rst
odoo/addons/account_invoice_overdue_reminder/security/ir.model.access.csv
odoo/addons/account_invoice_overdue_reminder/security/ir_rule.xml
odoo/addons/account_invoice_overdue_reminder/static/description/icon.png
odoo/addons/account_invoice_overdue_reminder/static/description/index.html
odoo13_addon_account_invoice_overdue_reminder-13.0.1.3.0.dist-info/METADATA
odoo13_addon_account_invoice_overdue_reminder-13.0.1.3.0.dist-info/WHEEL
odoo13_addon_account_invoice_overdue_reminder-13.0.1.3.0.dist-info/top_level.txt
odoo13_addon_account_invoice_overdue_reminder-13.0.1.3.0.dist-info/RECORD
